exoiris/__init__.py
exoiris/binning.py
exoiris/ephemeris.py
exoiris/exoiris.py
exoiris/ldtkld.py
exoiris/loglikelihood.py
exoiris/spotmodel.py
exoiris/tsdata.py
exoiris/tslpf.py
exoiris/tsmodel.py
exoiris/util.py
exoiris/wlpf.py
exoiris-0.23.2.dist-info/licenses/LICENSE
exoiris-0.23.2.dist-info/METADATA
exoiris-0.23.2.dist-info/WHEEL
exoiris-0.23.2.dist-info/top_level.txt
exoiris-0.23.2.dist-info/RECORD
