Metadata-Version: 2.4
Name: ExoIris
Version: 0.23.2
Summary: Easy and robust exoplanet transmission spectroscopy.
Author-email: Hannu Parviainen <hannu@iac.es>
License: GPLv3
Project-URL: homepage, https://github.com/hpparvi/ExoIris
Keywords: astronomy,astrophysics,exoplanets
Classifier: Topic :: Scientific/Engineering
Classifier: Intended Audience :: Science/Research
Classifier: Intended Audience :: Developers
Classifier: Development Status :: 5 - Production/Stable
Classifier: License :: OSI Approved :: GNU General Public License v3 (GPLv3)
Classifier: Operating System :: OS Independent
Classifier: Programming Language :: Python
Requires-Python: >=3.10
License-File: LICENSE
Requires-Dist: pytransit>=2.6.15
Requires-Dist: ldtk>=1.8.5
Requires-Dist: numpy
Requires-Dist: scipy
Requires-Dist: numba
Requires-Dist: emcee
Requires-Dist: matplotlib
Requires-Dist: celerite2
Requires-Dist: pandas
Requires-Dist: xarray
Requires-Dist: seaborn
Requires-Dist: astropy
Requires-Dist: uncertainties
Requires-Dist: scikit-learn
Dynamic: license-file
